guolei_py3_images/__init__.py
guolei_py3_images/imgkit.py
guolei_py3_images/library/__init__.py
guolei_py3_images/library/imgkit.py
guolei_py3_images-2.0.0.dist-info/LICENSE
guolei_py3_images-2.0.0.dist-info/METADATA
guolei_py3_images-2.0.0.dist-info/WHEEL
guolei_py3_images-2.0.0.dist-info/top_level.txt
guolei_py3_images-2.0.0.dist-info/RECORD
