Metadata-Version: 2.1
Name: guolei-py3-images
Version: 2.0.0
Summary: 郭磊 Images API
Home-page: https://github.com/guolei19850528/guolei_py3_images
Author: guolei
Author-email: 174000902@qq.com
License: MIT
Requires-Python: >=3.0
License-File: LICENSE
Requires-Dist: addict
Requires-Dist: retrying
Requires-Dist: jsonschema
Requires-Dist: imgkit
Requires-Dist: Pillow
